README
setup.cfg
setup.py
geomobilejp/__init__.py
geomobilejp.egg-info/PKG-INFO
geomobilejp.egg-info/SOURCES.txt
geomobilejp.egg-info/dependency_links.txt
geomobilejp.egg-info/entry_points.txt
geomobilejp.egg-info/not-zip-safe
geomobilejp.egg-info/top_level.txt
geomobilejp/converter/__init__.py
geomobilejp/converter/datum.py
geomobilejp/converter/format.py
geomobilejp/converter/point.py
geomobilejp/iarea/__init__.py
geomobilejp/iarea/area.py
geomobilejp/iarea/areadata.py
geomobilejp/iarea/aura.py
geomobilejp/iarea/next.py
tests/converter/__init__.py
tests/converter/test_contruct.py
tests/converter/test_convert.py
tests/converter/test_datum.py
tests/converter/test_format.py
tests/converter/test_point.py