Metadata-Version: 1.0
Name: geomobilejp
Version: 0.1.0
Summary: PyGeoMobileJP
Home-page: http://code.google.com/p/pygeomobilejp/
Author: Chihio Sakatoku
Author-email: csakatoku@mac.com
License: MIT License
Platform: any
Classifier: Development Status :: 4 - Beta
Classifier: License :: OSI Approved :: MIT License
Classifier: Programming Language :: Python
Classifier: Operating System :: OS Independent
Classifier: Topic :: Software Development :: Libraries :: Python Modules
